growpal/libclustering.py
growpal/libdescriptors.py
growpal/libdisc_usr.py
growpal/libgrowpal.py
growpal/libselect_clustering.py
growpal/v.check.py
growpal/x.main.py
growpal-0.0.6.dist-info/licenses/LICENSE
growpal-0.0.6.dist-info/METADATA
growpal-0.0.6.dist-info/WHEEL
growpal-0.0.6.dist-info/top_level.txt
growpal-0.0.6.dist-info/RECORD
