Metadata-Version: 2.4
Name: growpal
Version: 0.0.6
Summary: Growth Pattern Algorithm
Author-email: Filiberto Ortiz Chi <fortiz666@gmail.com>
License: MIT
Project-URL: Homepage, https://github.com/fortizchi/growpal
License-File: LICENSE
Requires-Dist: dscribe
Requires-Dist: ase
Requires-Dist: aegon==1.2.4
Dynamic: license-file
